<fragment>
	<tag>
		<description>Renders a grid</description>
		<display-name>Grid</display-name>
		<name>grid</name>
		<tag-class>com.jslsolucoes.tagria.tag.html.v4.tag.grid.GridTag</tag-class>
		<body-content>scriptless</body-content>
		<attribute>
			<description>It indicates the collection to be iterated by the component</description>
			<name>data</name>
			<required>true</required>
			<rtexprvalue>true</rtexprvalue>
			<type>java.util.Collection</type>
		</attribute>
		<attribute>
			<description>It indicates the name of the variable java to be made available the object of iteration</description>
			<name>var</name>
			<required>true</required>
			<rtexprvalue>true</rtexprvalue>
			<type>java.lang.String</type>
		</attribute>
		<attribute>
			<description>It indicates the name of the variable to be available to current iteration</description>
			<name>varStatus</name>
			<rtexprvalue>true</rtexprvalue>
			<type>java.lang.String</type>
		</attribute>
		<attribute>
			<description>Indicates the label component</description>
			<name>label</name>
			<rtexprvalue>true</rtexprvalue>
			<type>java.lang.String</type>
		</attribute>
		<attribute>
			<description>Indicates the url component a ser utilizada caso haja paginação</description>
			<name>url</name>
			<rtexprvalue>true</rtexprvalue>
			<type>java.lang.String</type>
		</attribute>
		<attribute>
			<description>It indicates whether the component should be rendered</description>
			<name>rendered</name>
			<rtexprvalue>true</rtexprvalue>
			<type>java.lang.Boolean</type>
		</attribute>
		<attribute>
			<description>Indicates the component title when there are no lines available</description>
			<name>noRowText</name>
			<rtexprvalue>true</rtexprvalue>
			<type>java.lang.String</type>
		</attribute>
		<attribute>
			<description>Indicates the component title key (i18n) when there are no lines available</description>
			<name>noRowTextKey</name>
			<rtexprvalue>true</rtexprvalue>
			<type>java.lang.String</type>
		</attribute>
		<example>
			&lt;html:grid var="person" data="${ persons }" label="My grid"&gt;
				&lt;html:grid-export/&gt;
				&lt;html:grid-paginate totalResults="${ totalResults }"&gt;&lt;/html:grid-paginate&gt;
				&lt;html:grid-search/&gt;
				&lt;html:grid-toolbar&gt;
					&lt;html:alert state="danger"&gt;my toolbar&lt;/html:alert&gt;
				&lt;/html:grid-toolbar&gt;
				&lt;html:grid-header&gt;
					&lt;html:grid-column label="Column 1" align="left" exportable="true"&gt;&lt;/html:grid-column&gt;
					&lt;html:grid-column label="Column 2" align="center" exportable="true"&gt;&lt;/html:grid-column&gt;
					&lt;html:grid-column label="Column 3" align="center" exportable="true"&gt;&lt;/html:grid-column&gt;
				&lt;/html:grid-header&gt;
				&lt;html:grid-body&gt;
					&lt;html:grid-column-data align="right" exportable="true"&gt;
						${ person.name }
					&lt;/html:grid-column-data&gt;
					&lt;html:grid-column-data align="center" exportable="true" booleanType="true"&gt;
						${ person.likeChocolate }
					&lt;/html:grid-column-data&gt;
					&lt;html:grid-column-data align="center" exportable="true" collapsable="true"&gt;
						${ person.cpf }
					&lt;/html:grid-column-data&gt;
				&lt;/html:grid-body&gt;
			&lt;/html:grid&gt;
		</example>
	</tag>
	
	<tag>
		<description>Renders a grid paginate data</description>
		<display-name>Grid</display-name>
		<name>grid-paginate</name>
		<tag-class>com.jslsolucoes.tagria.tag.html.v4.tag.grid.GridPaginateTag</tag-class>
		<body-content>scriptless</body-content>
		<attribute>
			<description>Indicates the total number of records in component</description>
			<name>totalResults</name>
			<required>true</required>
			<rtexprvalue>true</rtexprvalue>
			<type>java.lang.Integer</type>
		</attribute>
		<attribute>
			<description>It indicates the default number of results per page. Default: 60. Options: 20,40,60,80,100</description>
			<name>resultsPerPage</name>
			<rtexprvalue>true</rtexprvalue>
			<type>java.lang.Integer</type>
		</attribute>
		<example>
			&lt;html:grid var="person" data="${ persons }" label="My grid"&gt;
				&lt;html:grid-export/&gt;
				&lt;html:grid-paginate totalResults="${ totalResults }"&gt;&lt;/html:grid-paginate&gt;
				&lt;html:grid-search/&gt;
				&lt;html:grid-toolbar&gt;
					&lt;html:alert state="danger"&gt;my toolbar&lt;/html:alert&gt;
				&lt;/html:grid-toolbar&gt;
				&lt;html:grid-header&gt;
					&lt;html:grid-column label="Column 1" align="left" exportable="true"&gt;&lt;/html:grid-column&gt;
					&lt;html:grid-column label="Column 2" align="center" exportable="true"&gt;&lt;/html:grid-column&gt;
					&lt;html:grid-column label="Column 3" align="center" exportable="true"&gt;&lt;/html:grid-column&gt;
				&lt;/html:grid-header&gt;
				&lt;html:grid-body&gt;
					&lt;html:grid-column-data align="right" exportable="true"&gt;
						${ person.name }
					&lt;/html:grid-column-data&gt;
					&lt;html:grid-column-data align="center" exportable="true" booleanType="true"&gt;
						${ person.likeChocolate }
					&lt;/html:grid-column-data&gt;
					&lt;html:grid-column-data align="center" exportable="true" collapsable="true"&gt;
						${ person.cpf }
					&lt;/html:grid-column-data&gt;
				&lt;/html:grid-body&gt;
			&lt;/html:grid&gt;
		</example>
	</tag>
	
	<tag>
		<description>Renders a grid search data</description>
		<display-name>Grid</display-name>
		<name>grid-search</name>
		<tag-class>com.jslsolucoes.tagria.tag.html.v4.tag.grid.GridSearchTag</tag-class>
		<body-content>scriptless</body-content>
		<example>
			&lt;html:grid var="person" data="${ persons }" label="My grid"&gt;
				&lt;html:grid-export/&gt;
				&lt;html:grid-paginate totalResults="${ totalResults }"&gt;&lt;/html:grid-paginate&gt;
				&lt;html:grid-search/&gt;
				&lt;html:grid-toolbar&gt;
					&lt;html:alert state="danger"&gt;my toolbar&lt;/html:alert&gt;
				&lt;/html:grid-toolbar&gt;
				&lt;html:grid-header&gt;
					&lt;html:grid-column label="Column 1" align="left" exportable="true"&gt;&lt;/html:grid-column&gt;
					&lt;html:grid-column label="Column 2" align="center" exportable="true"&gt;&lt;/html:grid-column&gt;
					&lt;html:grid-column label="Column 3" align="center" exportable="true"&gt;&lt;/html:grid-column&gt;
				&lt;/html:grid-header&gt;
				&lt;html:grid-body&gt;
					&lt;html:grid-column-data align="right" exportable="true"&gt;
						${ person.name }
					&lt;/html:grid-column-data&gt;
					&lt;html:grid-column-data align="center" exportable="true" booleanType="true"&gt;
						${ person.likeChocolate }
					&lt;/html:grid-column-data&gt;
					&lt;html:grid-column-data align="center" exportable="true" collapsable="true"&gt;
						${ person.cpf }
					&lt;/html:grid-column-data&gt;
				&lt;/html:grid-body&gt;
			&lt;/html:grid&gt;
		</example>
	</tag>
	
	<tag>
		<description>Renders a grid export data</description>
		<display-name>Grid</display-name>
		<name>grid-export</name>
		<tag-class>com.jslsolucoes.tagria.tag.html.v4.tag.grid.GridExportTag</tag-class>
		<body-content>scriptless</body-content>
		<attribute>
			<description>It indicates if export support pdf file. Default: true</description>
			<name>pdf</name>
			<rtexprvalue>true</rtexprvalue>
			<type>java.lang.Boolean</type>
		</attribute>
		<attribute>
			<description>It indicates if export support xlsx file. Default: true</description>
			<name>xlsx</name>
			<rtexprvalue>true</rtexprvalue>
			<type>java.lang.Boolean</type>
		</attribute>
		<attribute>
			<description>It indicates if export support csv file. Default: true</description>
			<name>csv</name>
			<rtexprvalue>true</rtexprvalue>
			<type>java.lang.Boolean</type>
		</attribute>
		<attribute>
			<description>It indicates if export support xml file. Default: true</description>
			<name>xml</name>
			<rtexprvalue>true</rtexprvalue>
			<type>java.lang.Boolean</type>
		</attribute>
		<example>
			&lt;html:grid var="person" data="${ persons }" label="My grid"&gt;
				&lt;html:grid-export/&gt;
				&lt;html:grid-paginate totalResults="${ totalResults }"&gt;&lt;/html:grid-paginate&gt;
				&lt;html:grid-search/&gt;
				&lt;html:grid-toolbar&gt;
					&lt;html:alert state="danger"&gt;my toolbar&lt;/html:alert&gt;
				&lt;/html:grid-toolbar&gt;
				&lt;html:grid-header&gt;
					&lt;html:grid-column label="Column 1" align="left" exportable="true"&gt;&lt;/html:grid-column&gt;
					&lt;html:grid-column label="Column 2" align="center" exportable="true"&gt;&lt;/html:grid-column&gt;
					&lt;html:grid-column label="Column 3" align="center" exportable="true"&gt;&lt;/html:grid-column&gt;
				&lt;/html:grid-header&gt;
				&lt;html:grid-body&gt;
					&lt;html:grid-column-data align="right" exportable="true"&gt;
						${ person.name }
					&lt;/html:grid-column-data&gt;
					&lt;html:grid-column-data align="center" exportable="true" booleanType="true"&gt;
						${ person.likeChocolate }
					&lt;/html:grid-column-data&gt;
					&lt;html:grid-column-data align="center" exportable="true" collapsable="true"&gt;
						${ person.cpf }
					&lt;/html:grid-column-data&gt;
				&lt;/html:grid-body&gt;
			&lt;/html:grid&gt;
		</example>
	</tag>
	
	<tag>
		<description>Renders a grid header</description>
		<display-name>Grid</display-name>
		<name>grid-header</name>
		<tag-class>com.jslsolucoes.tagria.tag.html.v4.tag.grid.GridHeaderTag</tag-class>
		<body-content>scriptless</body-content>
		<example>
			&lt;html:grid var="person" data="${ persons }" label="My grid"&gt;
				&lt;html:grid-export/&gt;
				&lt;html:grid-paginate totalResults="${ totalResults }"&gt;&lt;/html:grid-paginate&gt;
				&lt;html:grid-search/&gt;
				&lt;html:grid-toolbar&gt;
					&lt;html:alert state="danger"&gt;my toolbar&lt;/html:alert&gt;
				&lt;/html:grid-toolbar&gt;
				&lt;html:grid-header&gt;
					&lt;html:grid-column label="Column 1" align="left" exportable="true"&gt;&lt;/html:grid-column&gt;
					&lt;html:grid-column label="Column 2" align="center" exportable="true"&gt;&lt;/html:grid-column&gt;
					&lt;html:grid-column label="Column 3" align="center" exportable="true"&gt;&lt;/html:grid-column&gt;
				&lt;/html:grid-header&gt;
				&lt;html:grid-body&gt;
					&lt;html:grid-column-data align="right" exportable="true"&gt;
						${ person.name }
					&lt;/html:grid-column-data&gt;
					&lt;html:grid-column-data align="center" exportable="true" booleanType="true"&gt;
						${ person.likeChocolate }
					&lt;/html:grid-column-data&gt;
					&lt;html:grid-column-data align="center" exportable="true" collapsable="true"&gt;
						${ person.cpf }
					&lt;/html:grid-column-data&gt;
				&lt;/html:grid-body&gt;
			&lt;/html:grid&gt;
		</example>
	</tag>
	
	<tag>
		<description>Renders a grid header column</description>
		<display-name>Grid</display-name>
		<name>grid-column</name>
		<tag-class>com.jslsolucoes.tagria.tag.html.v4.tag.grid.GridColumnTag</tag-class>
		<body-content>scriptless</body-content>
		<attribute>
			<description>It indicates whether the column should be exported</description>
			<name>exportable</name>
			<rtexprvalue>true</rtexprvalue>
			<type>java.lang.Boolean</type>
		</attribute>
		<attribute>
			<description>Indicates the alignment of the content. Default: left. Options: left, center, right</description>
			<name>align</name>
			<rtexprvalue>true</rtexprvalue>
			<type>java.lang.String</type>
		</attribute>
		<attribute>
			<description>Indicates the label component</description>
			<name>label</name>
			<rtexprvalue>true</rtexprvalue>
			<type>java.lang.String</type>
		</attribute>
		<attribute>
			<description>Indicates the label key (i18n) component</description>
			<name>labelKey</name>
			<rtexprvalue>true</rtexprvalue>
			<type>java.lang.String</type>
		</attribute>
		<example>
			&lt;html:grid var="person" data="${ persons }" label="My grid"&gt;
				&lt;html:grid-export/&gt;
				&lt;html:grid-paginate totalResults="${ totalResults }"&gt;&lt;/html:grid-paginate&gt;
				&lt;html:grid-search/&gt;
				&lt;html:grid-toolbar&gt;
					&lt;html:alert state="danger"&gt;my toolbar&lt;/html:alert&gt;
				&lt;/html:grid-toolbar&gt;
				&lt;html:grid-header&gt;
					&lt;html:grid-column label="Column 1" align="left" exportable="true"&gt;&lt;/html:grid-column&gt;
					&lt;html:grid-column label="Column 2" align="center" exportable="true"&gt;&lt;/html:grid-column&gt;
					&lt;html:grid-column label="Column 3" align="center" exportable="true"&gt;&lt;/html:grid-column&gt;
				&lt;/html:grid-header&gt;
				&lt;html:grid-body&gt;
					&lt;html:grid-column-data align="right" exportable="true"&gt;
						${ person.name }
					&lt;/html:grid-column-data&gt;
					&lt;html:grid-column-data align="center" exportable="true" booleanType="true"&gt;
						${ person.likeChocolate }
					&lt;/html:grid-column-data&gt;
					&lt;html:grid-column-data align="center" exportable="true" collapsable="true"&gt;
						${ person.cpf }
					&lt;/html:grid-column-data&gt;
				&lt;/html:grid-body&gt;
			&lt;/html:grid&gt;
		</example>
	</tag>
	
	<tag>
		<description>Renders a grid body</description>
		<display-name>Grid</display-name>
		<name>grid-body</name>
		<tag-class>com.jslsolucoes.tagria.tag.html.v4.tag.grid.GridBodyTag</tag-class>
		<body-content>scriptless</body-content>
		<example>
			&lt;html:grid var="person" data="${ persons }" label="My grid"&gt;
				&lt;html:grid-export/&gt;
				&lt;html:grid-paginate totalResults="${ totalResults }"&gt;&lt;/html:grid-paginate&gt;
				&lt;html:grid-search/&gt;
				&lt;html:grid-toolbar&gt;
					&lt;html:alert state="danger"&gt;my toolbar&lt;/html:alert&gt;
				&lt;/html:grid-toolbar&gt;
				&lt;html:grid-header&gt;
					&lt;html:grid-column label="Column 1" align="left" exportable="true"&gt;&lt;/html:grid-column&gt;
					&lt;html:grid-column label="Column 2" align="center" exportable="true"&gt;&lt;/html:grid-column&gt;
					&lt;html:grid-column label="Column 3" align="center" exportable="true"&gt;&lt;/html:grid-column&gt;
				&lt;/html:grid-header&gt;
				&lt;html:grid-body&gt;
					&lt;html:grid-column-data align="right" exportable="true"&gt;
						${ person.name }
					&lt;/html:grid-column-data&gt;
					&lt;html:grid-column-data align="center" exportable="true" booleanType="true"&gt;
						${ person.likeChocolate }
					&lt;/html:grid-column-data&gt;
					&lt;html:grid-column-data align="center" exportable="true" collapsable="true"&gt;
						${ person.cpf }
					&lt;/html:grid-column-data&gt;
				&lt;/html:grid-body&gt;
			&lt;/html:grid&gt;
		</example>
	</tag>
	
	<tag>
		<description>Renders a grid body footer</description>
		<display-name>Grid</display-name>
		<name>grid-footer</name>
		<tag-class>com.jslsolucoes.tagria.tag.html.v4.tag.grid.GridFooterTag</tag-class>
		<body-content>scriptless</body-content>
		<example>
			&lt;html:grid var="person" data="${ persons }" label="My grid"&gt;
				&lt;html:grid-export/&gt;
				&lt;html:grid-paginate totalResults="${ totalResults }"&gt;&lt;/html:grid-paginate&gt;
				&lt;html:grid-search/&gt;
				&lt;html:grid-toolbar&gt;
					&lt;html:alert state="danger"&gt;my toolbar&lt;/html:alert&gt;
				&lt;/html:grid-toolbar&gt;
				&lt;html:grid-header&gt;
					&lt;html:grid-column label="Column 1" align="left" exportable="true"&gt;&lt;/html:grid-column&gt;
					&lt;html:grid-column label="Column 2" align="center" exportable="true"&gt;&lt;/html:grid-column&gt;
					&lt;html:grid-column label="Column 3" align="center" exportable="true"&gt;&lt;/html:grid-column&gt;
				&lt;/html:grid-header&gt;
				&lt;html:grid-body&gt;
					&lt;html:grid-column-data align="right" exportable="true"&gt;
						${ person.name }
					&lt;/html:grid-column-data&gt;
					&lt;html:grid-column-data align="center" exportable="true" booleanType="true"&gt;
						${ person.likeChocolate }
					&lt;/html:grid-column-data&gt;
					&lt;html:grid-column-data align="center" exportable="true" collapsable="true"&gt;
						${ person.cpf }
					&lt;/html:grid-column-data&gt;
				&lt;/html:grid-body&gt;
			&lt;/html:grid&gt;
		</example>
	</tag>
	
	<tag>
		<description>Renders a grid data column</description>
		<display-name>Grid</display-name>
		<name>grid-column-data</name>
		<tag-class>com.jslsolucoes.tagria.tag.html.v4.tag.grid.GridColumnDataTag</tag-class>
		<body-content>scriptless</body-content>
		<attribute>
			<description>Indicates the alignment of the content. Default: left. Options: left, center, right</description>
			<name>align</name>
			<rtexprvalue>true</rtexprvalue>
			<type>java.lang.String</type>
		</attribute>
		<attribute>
			<description>Indicates the component state. Default: default. Options: danger, info, success, default</description>
			<name>state</name>
			<rtexprvalue>true</rtexprvalue>
			<type>java.lang.String</type>
		</attribute>
		<attribute>
			<description>Indicates whether the component value is of type boolean. Default false</description>
			<name>booleanType</name>
			<rtexprvalue>true</rtexprvalue>
			<type>java.lang.Boolean</type>
		</attribute>
		<attribute>
			<description>It indicates a css class to the component</description>
			<name>cssClass</name>
			<rtexprvalue>true</rtexprvalue>
			<type>java.lang.String</type>
		</attribute>
		<attribute>
			<description>It indicates whether the column should be collapsable. Default false</description>
			<name>collapsable</name>
			<rtexprvalue>true</rtexprvalue>
			<type>java.lang.Boolean</type>
		</attribute>
		<attribute>
			<description>It indicates whether the column should be exported. Default false</description>
			<name>exportable</name>
			<rtexprvalue>true</rtexprvalue>
			<type>java.lang.Boolean</type>
		</attribute>
		<example>
			&lt;html:grid var="person" data="${ persons }" label="My grid"&gt;
				&lt;html:grid-export/&gt;
				&lt;html:grid-paginate totalResults="${ totalResults }"&gt;&lt;/html:grid-paginate&gt;
				&lt;html:grid-search/&gt;
				&lt;html:grid-toolbar&gt;
					&lt;html:alert state="danger"&gt;my toolbar&lt;/html:alert&gt;
				&lt;/html:grid-toolbar&gt;
				&lt;html:grid-header&gt;
					&lt;html:grid-column label="Column 1" align="left" exportable="true"&gt;&lt;/html:grid-column&gt;
					&lt;html:grid-column label="Column 2" align="center" exportable="true"&gt;&lt;/html:grid-column&gt;
					&lt;html:grid-column label="Column 3" align="center" exportable="true"&gt;&lt;/html:grid-column&gt;
				&lt;/html:grid-header&gt;
				&lt;html:grid-body&gt;
					&lt;html:grid-column-data align="right" exportable="true"&gt;
						${ person.name }
					&lt;/html:grid-column-data&gt;
					&lt;html:grid-column-data align="center" exportable="true" booleanType="true"&gt;
						${ person.likeChocolate }
					&lt;/html:grid-column-data&gt;
					&lt;html:grid-column-data align="center" exportable="true" collapsable="true"&gt;
						${ person.cpf }
					&lt;/html:grid-column-data&gt;
				&lt;/html:grid-body&gt;
			&lt;/html:grid&gt;
		</example>
	</tag>
	
	<tag>
		<description>Renders a grid toolbar</description>
		<display-name>Grid</display-name>
		<name>grid-toolbar</name>
		<tag-class>com.jslsolucoes.tagria.tag.html.v4.tag.grid.GridToolbarTag</tag-class>
		<body-content>scriptless</body-content>
		<attribute>
			<description>It indicates whether the component should be rendered</description>
			<name>rendered</name>
			<rtexprvalue>true</rtexprvalue>
			<type>java.lang.Boolean</type>
		</attribute>
		<example>
			&lt;html:grid var="person" data="${ persons }" label="My grid"&gt;
				&lt;html:grid-export/&gt;
				&lt;html:grid-paginate totalResults="${ totalResults }"&gt;&lt;/html:grid-paginate&gt;
				&lt;html:grid-search/&gt;
				&lt;html:grid-toolbar&gt;
					&lt;html:alert state="danger"&gt;my toolbar&lt;/html:alert&gt;
				&lt;/html:grid-toolbar&gt;
				&lt;html:grid-header&gt;
					&lt;html:grid-column label="Column 1" align="left" exportable="true"&gt;&lt;/html:grid-column&gt;
					&lt;html:grid-column label="Column 2" align="center" exportable="true"&gt;&lt;/html:grid-column&gt;
					&lt;html:grid-column label="Column 3" align="center" exportable="true"&gt;&lt;/html:grid-column&gt;
				&lt;/html:grid-header&gt;
				&lt;html:grid-body&gt;
					&lt;html:grid-column-data align="right" exportable="true"&gt;
						${ person.name }
					&lt;/html:grid-column-data&gt;
					&lt;html:grid-column-data align="center" exportable="true" booleanType="true"&gt;
						${ person.likeChocolate }
					&lt;/html:grid-column-data&gt;
					&lt;html:grid-column-data align="center" exportable="true" collapsable="true"&gt;
						${ person.cpf }
					&lt;/html:grid-column-data&gt;
				&lt;/html:grid-body&gt;
			&lt;/html:grid&gt;
		</example>
	</tag>
	
	
	
</fragment>